Metadata-Version: 1.0
Name: distributions18
Version: 0.1
Summary: Gaussian and Binomial distributions
Home-page: UNKNOWN
Author: Andrew Alarcon
Author-email: UNKNOWN
License: UNKNOWN
Platform: UNKNOWN
